visualizer/ExampleNet.py
visualizer/Visualizer.py
visualizer/__init__.py
visualizer_torch-0.0.4.dist-info/LICENSE.txt
visualizer_torch-0.0.4.dist-info/METADATA
visualizer_torch-0.0.4.dist-info/WHEEL
visualizer_torch-0.0.4.dist-info/top_level.txt
visualizer_torch-0.0.4.dist-info/RECORD
