Metadata-Version: 2.1
Name: visualizer-torch
Version: 0.0.4
Summary: UNKNOWN
Home-page: https://github.com/bironsecret/pytorch-model-visualizer
Author: neonsecret
License: UNKNOWN
Download-URL: https://github.com/bironsecret/pytorch-model-visualizer/archive/refs/tags/v0.0.3.tar.gz
Platform: UNKNOWN
Classifier: Programming Language :: Python :: 3
Classifier: License :: OSI Approved :: MIT License
Classifier: Operating System :: OS Independent
Requires-Python: >=3.6
